better_rich_prompts/__init__.py
better_rich_prompts/prompt.py
better_rich_prompts-1.0.2.dist-info/METADATA
better_rich_prompts-1.0.2.dist-info/WHEEL
better_rich_prompts-1.0.2.dist-info/RECORD
