Metadata-Version: 2.1
Name: better-rich-prompts
Version: 1.0.2
Summary: Improved prompts for rich.
Home-page: https://github.com/EwenLo/better-rich-prompts
License: MIT
Author: Ewen Lorimer
Author-email: ewen@ewenlorimer.ca
Requires-Python: >=3.7.0
Classifier: Development Status :: 5 - Production/Stable
Classifier: Environment :: Console
Classifier: Framework :: IPython
Classifier: Intended Audience :: Developers
Classifier: License :: OSI Approved :: MIT License
Classifier: Operating System :: MacOS
Classifier: Operating System :: Microsoft :: Windows
Classifier: Operating System :: POSIX :: Linux
Classifier: Programming Language :: Python :: 3
Classifier: Programming Language :: Python :: 3.7
Classifier: Programming Language :: Python :: 3.8
Classifier: Programming Language :: Python :: 3.9
Classifier: Programming Language :: Python :: 3.10
Classifier: Programming Language :: Python :: 3.11
Classifier: Typing :: Typed
Provides-Extra: jupyter
Requires-Dist: rich (>=3.3.2)
Project-URL: Documentation, https://github.com/EwenLo/better-rich-prompts/
